{

  "name": "gridsome-plugin-remote-image",
  "links": [{
      "link": {
        "title": "Getting started",
        "url": "#"
      },
      "children": [{
          "link": {
            "title": "Introduction",
            "url": "/"
          }
        },
        {
          "link": {
            "title": "Configuration",
            "url": "/configuration"
          }
        },
        {
          "link": {
            "title": "Example",
            "url": "/example"
          }
        }
      ]
    }
  ]
}